[
  {
    "id": "mneUI9j5R4yTKe63kwWy",
    "userID": "",
    "profilePicture": "https://lh3.googleusercontent.com/a/ACg8ocI-pEwJSsYP9SExAOOUkcTdGUYCZPWTgHwOrLswkEFKmtkOc_Q=s96-c",
    "displayName": "Ron W.",
    "position": "",
    "location": "Red Oak, Texas",
    "verified": true,
    "duration": 30.348481,
    "likes": 0,
    "loves": 0,
    "views": 0,
    "profileURL": "https://reelcareer.co/u/?u=ql9uEsdGRrY0Jpu8AaVvQafxvBH2",
    "thumbnailURL": "",
    "videoResumeURL": "https://firebasestorage.googleapis.com/v0/b/reelcareer-cb4b0.appspot.com/o/videoResumes%2Fql9uEsdGRrY0Jpu8AaVvQafxvBH2%2Fql9uEsdGRrY0Jpu8AaVvQafxvBH2-2025-01-14T19%3A25%3A44.950Z-reel.mp4?alt=media&token=0d2892d6-7c9e-4d07-b2d8-e386a31c93f9",
    "videoResumeCaptions": "test the #hash #tags",
    "tags": [
      "#hash",
      "#tags"
    ],
    "timestamp": {
      "seconds": 1736882793,
      "nanoseconds": 535000000
    }
  },
  {
    "id": "yExoQuM7AUeqfFPrSfNJ",
    "userID": "",
    "profilePicture": "https://lh3.googleusercontent.com/a/ACg8ocI-pEwJSsYP9SExAOOUkcTdGUYCZPWTgHwOrLswkEFKmtkOc_Q=s96-c",
    "displayName": "Ron W.",
    "position": "",
    "location": "Red Oak, Texas",
    "verified": true,
    "duration": 6.013968,
    "likes": 5,
    "loves": 0,
    "views": 37,
    "profileURL": "https://reelcareer.co/u/?u=ql9uEsdGRrY0Jpu8AaVvQafxvBH2",
    "thumbnailURL": "",
    "videoResumeURL": "https://firebasestorage.googleapis.com/v0/b/reelcareer-cb4b0.appspot.com/o/videoResumes%2Fql9uEsdGRrY0Jpu8AaVvQafxvBH2%2Fql9uEsdGRrY0Jpu8AaVvQafxvBH2-2024-12-13T12%3A02%3A38.091Z-reel.mp4?alt=media&token=5ddc47f7-6dec-4a53-88f1-76ac5da998ca",
    "videoResumeCaptions": "ReelCareer 4nd video",
    "tags": [
      "financex",
      "test"
    ],
    "timestamp": {
      "seconds": 1734091364,
      "nanoseconds": 920000000
    }
  },
  {
    "id": "QJF2BIw5ztPExSssUK9e",
    "userID": "",
    "profilePicture": "https://lh3.googleusercontent.com/a/ACg8ocI-pEwJSsYP9SExAOOUkcTdGUYCZPWTgHwOrLswkEFKmtkOc_Q=s96-c",
    "displayName": "Ron W.",
    "position": "",
    "location": "Red Oak, Texas",
    "verified": true,
    "duration": 6.013968,
    "likes": 2,
    "loves": 0,
    "views": 15,
    "profileURL": "https://reelcareer.co/u/?u=ql9uEsdGRrY0Jpu8AaVvQafxvBH2",
    "thumbnailURL": "",
    "videoResumeURL": "https://firebasestorage.googleapis.com/v0/b/reelcareer-cb4b0.appspot.com/o/videoResumes%2Fql9uEsdGRrY0Jpu8AaVvQafxvBH2%2Fql9uEsdGRrY0Jpu8AaVvQafxvBH2-2024-12-13T11%3A44%3A53.947Z-reel.mp4?alt=media&token=420cfbd5-b148-49e0-ba1d-5095ea031da8",
    "videoResumeCaptions": "ReelCareer 3rd video",
    "tags": [
      "financex",
      "test"
    ],
    "timestamp": {
      "seconds": 1734090294,
      "nanoseconds": 711000000
    }
  },
  {
    "id": "I2AtnMTZdjoMmexdOvUJ",
    "userID": "",
    "profilePicture": "https://lh3.googleusercontent.com/a/ACg8ocI-pEwJSsYP9SExAOOUkcTdGUYCZPWTgHwOrLswkEFKmtkOc_Q=s96-c",
    "displayName": "Ron W.",
    "position": "",
    "location": "Red Oak, Texas",
    "verified": true,
    "duration": 6.013968,
    "likes": 0,
    "loves": 0,
    "views": 14,
    "profileURL": "https://reelcareer.co/u/?u=ql9uEsdGRrY0Jpu8AaVvQafxvBH2",
    "thumbnailURL": "",
    "videoResumeURL": "https://firebasestorage.googleapis.com/v0/b/reelcareer-cb4b0.appspot.com/o/videoResumes%2Fql9uEsdGRrY0Jpu8AaVvQafxvBH2%2Fql9uEsdGRrY0Jpu8AaVvQafxvBH2-2024-12-09T01%3A34%3A59.575Z-reel.webm?alt=media&token=e3c6ea2c-6cbf-4e41-ad59-474f2aae3ad7",
    "videoResumeCaptions": "ReelCareer 2nd video",
    "tags": [
      "finance",
      "reelcareer.com",
      "job board",
      "new"
    ],
    "timestamp": {
      "seconds": 1733708101,
      "nanoseconds": 89000000
    }
  },
  {
    "id": "0cJA82Nn750wRZaUChMj",
    "userID": "",
    "profilePicture": "https://lh3.googleusercontent.com/a/ACg8ocI-pEwJSsYP9SExAOOUkcTdGUYCZPWTgHwOrLswkEFKmtkOc_Q=s96-c",
    "displayName": "Ron W.",
    "position": "",
    "location": "Red Oak, Texas",
    "verified": true,
    "duration": 6.013968,
    "likes": 0,
    "loves": 0,
    "views": 14,
    "profileURL": "https://reelcareer.co/u/?u=ql9uEsdGRrY0Jpu8AaVvQafxvBH2",
    "thumbnailURL": "",
    "videoResumeURL": "https://firebasestorage.googleapis.com/v0/b/reelcareer-cb4b0.appspot.com/o/videoResumes%2Fql9uEsdGRrY0Jpu8AaVvQafxvBH2%2Fql9uEsdGRrY0Jpu8AaVvQafxvBH2-2024-12-08T23%3A57%3A17.771Z-reel.webm?alt=media&token=359bf9ee-57c3-4bb9-8bde-8f326b51d4ca",
    "videoResumeCaptions": "Our First Reel",
    "tags": [
      "finance",
      "reelcareer.co",
      "job board",
      "jobs"
    ],
    "timestamp": {
      "seconds": 1733702239,
      "nanoseconds": 702000000
    }
  }
]